avcheck/__init__.py
avcheck/client.py
avcheck/exceptions.py
avcheck-0.1.2.dist-info/METADATA
avcheck-0.1.2.dist-info/WHEEL
avcheck-0.1.2.dist-info/top_level.txt
avcheck-0.1.2.dist-info/RECORD
