Metadata-Version: 2.1
Name: avcheck
Version: 0.1.2
Summary: Python library to interact with AvCheck API
Home-page: https://github.com/NullBulgeOfficial/AVCheck-Python
Author: NullBulge
Author-email: contact@nullbulge.se
Project-URL: Bug Tracker, https://github.com/NullBulgeOfficial/AVCheck-Python/issues
Project-URL: Source Code, https://github.com/NullBulgeOfficial/AVCheck-Python
Classifier: Programming Language :: Python :: 3
Classifier: License :: OSI Approved :: MIT License
Classifier: Operating System :: OS Independent
Requires-Python: >=3.6
Requires-Dist: requests
